8080demo/power/pmu.v

module power_manager(
    input clk,                  // The master clock for this module
    input reset,                  // Synchronous reset
    input change_level_flag,
    input [2:0] change_level,        // First 1 bits select power_domain
    input change_power_mode_flag,
    input change_power_mode,        // Signal to change power_mode
    output wire power_domain_clk_0,
    output wire power_domain_clk_1
);
// wire and pll module
wire pll_clk;

SB_PLL40_CORE #(.FEEDBACK_PATH("SIMPLE"),
                  .PLLOUT_SELECT("GENCLK"),
                  .DIVR(4'b0000),
                  .DIVF(7'b0111111),
                  .DIVQ(3'b100),
                  .FILTER_RANGE(3'b001)
                 ) uut (
                         .REFERENCECLK(clk),
                         .PLLOUTCORE(pll_clk),
                         //.PLLOUTGLOBAL(clk),
                         // .LOCK(D5),
                         .RESETB(1'b1),
                         .BYPASS(1'b0)
                        );


// reg and warmboot module for reconfiguration



// Generated levels
`define SET_FR0 2'b00      // use for setting DIFF_LEVEL(2) 48.0
`define SET_FR1 2'b01      // use for setting NORMAL 12.0
`define SET_FR2 2'b10      // use for setting DIFF_LEVEL(1) 0.0012
`define SET_FR3 2'b11      // use for setting OFF 0


// Inner registers for divider
reg counter_reg_2 = 1'b0;

reg [12:0] counter_2 = 13'h0;


// Power domains registers and assigns
reg [1:0] power_domain_0_setter = 2'b01;
reg [1:0] power_domain_1_setter = 2'b10;

assign power_domain_clk_0 = (power_domain_0_setter == `SET_FR1) ? clk : 1'b0;
assign power_domain_clk_1 = (power_domain_1_setter == `SET_FR1) ? clk : (power_domain_1_setter == `SET_FR2) ? counter_reg_2 : (power_domain_1_setter == `SET_FR0) ? pll_clk : 1'b0;


// Synchronous sequential logic
always @ (posedge clk) begin
    if (reset) begin
        counter_2 <= 13'h0;
        counter_reg_2 <= 1'b0;
        power_domain_0_setter = 2'b01;
        power_domain_1_setter = 2'b10;
    end
    else begin

        if (counter_2) begin
            counter_2 <= counter_2 - 13'd1;
        end
        else begin
            counter_2 <= 13'd4999;
            counter_reg_2 <= !counter_reg_2;
        end

        // Controllers
        if (change_level_flag) begin
            if (change_level[2:2] == 1'b0) begin
                power_domain_0_setter <= change_level[1:0];
            end
            if (change_level[2:2] == 1'b1) begin
                power_domain_1_setter <= change_level[1:0];
            end
        end
        if (change_power_mode_flag) begin
            if (change_power_mode == 1'b0) begin
                power_domain_0_setter <= 2'b01;
                power_domain_1_setter <= 2'b10;
            end
            if (change_power_mode == 1'b1) begin
                power_domain_0_setter <= 2'b11;
                power_domain_1_setter <= 2'b11;
            end
        end

    end
end

endmodule

8080demo/power/pmu_tb.v
`include "pmu.v"
`timescale 1us/1us

module SB_PLL40_CORE(
    input REFERENCECLK,
    output PLLOUTCORE,
    output PLLOUTGLOBAL,
    input RESETB,
    input BYPASS
);

    parameter FEEDBACK_PATH = "SIMPLE";
    parameter PLLOUT_SELECT = "GENCLK";
    parameter DIVR = 4'b0000;
    parameter DIVF = 7'b0111111;
    parameter DIVQ = 3'b100;
    parameter FILTER_RANGE = 3'b001;

    assign PLLOUTCORE = REFERENCECLK;
    assign PLLOUTGLOBAL = REFERENCECLK;

endmodule

module SB_WARMBOOT(
    input BOOT,
    input S1,
    input S0
);
endmodule

module pmu_tb;

    initial begin
        $dumpfile("pmu_tb.vcd");
        $dumpvars;
        delay(500);
        pmu_changerSpeed = 1;
        pmu_busSpeed = 3'b101;
        delay(1);
        pmu_changerSpeed = 0;
        delay(800);
        $finish;
        //# 250E3 $finish;
        //# 1E6 $finish;
    end

    reg clk = 0;
    always #1 clk = !clk;
    reg clk2 = 0;
    always #2 clk2 = !clk2;

    reg pmu_changerSpeed = 0;
    reg [2:0] pmu_busSpeed = 3'b101;
    output pd_clk_0;
    output pd_clk_1;
    output pd_clk_2;



    power_manager pmu(
    .clk(clk),
    .reset(1'b0),
    .change_level_flag(pmu_changerSpeed),
    .change_level(pmu_busSpeed),
    //.change_power_mode_flag(),
    //.change_power_mode(),
    .power_domain_clk_0(pd_clk_0),
    .power_domain_clk_1(pd_clk_1)
    );

    task delay(input integer N); begin
        repeat(N) @(posedge clk);
    end endtask


endmodule

8080demo/power/pmu_tb.vcd
$date
	Mon Apr 29 00:35:45 2019
$end
$version
	Icarus Verilog
$end
$timescale
	1us
$end
$scope module pmu_tb $end
$var wire 1 ! pd_clk_2 $end
$var wire 1 " pd_clk_1 $end
$var wire 1 # pd_clk_0 $end
$var reg 1 $ clk $end
$var reg 1 % clk2 $end
$var reg 3 & pmu_busSpeed [2:0] $end
$var reg 1 ' pmu_changerSpeed $end
$scope module pmu $end
$var wire 3 ( change_level [2:0] $end
$var wire 1 ' change_level_flag $end
$var wire 1 ) change_power_mode $end
$var wire 1 * change_power_mode_flag $end
$var wire 1 $ clk $end
$var wire 1 + reset $end
$var wire 1 " power_domain_clk_1 $end
$var wire 1 # power_domain_clk_0 $end
$var wire 1 , pll_clk $end
$var reg 13 - counter_2 [12:0] $end
$var reg 1 . counter_reg_2 $end
$var reg 2 / power_domain_0_setter [1:0] $end
$var reg 2 0 power_domain_1_setter [1:0] $end
$scope module uut $end
$var wire 1 1 BYPASS $end
$var wire 1 , PLLOUTCORE $end
$var wire 1 2 PLLOUTGLOBAL $end
$var wire 1 $ REFERENCECLK $end
$var wire 1 3 RESETB $end
$upscope $end
$upscope $end
$scope task delay $end
$var integer 32 4 N [31:0] $end
$upscope $end
$upscope $end
$enddefinitions $end
#0
$dumpvars
b111110100 4
13
02
01
b10 0
b1 /
0.
b0 -
0,
0+
z*
z)
b101 (
0'
b101 &
0%
0$
0#
0"
z!
$end
#1
1"
1.
b1001110000111 -
1#
1,
12
1$
#2
0#
0,
02
0$
1%
#3
b1001110000110 -
1#
1,
12
1$
#4
0#
0,
02
0$
0%
#5
b1001110000101 -
1#
1,
12
1$
#6
0#
0,
02
0$
1%
#7
b1001110000100 -
1#
1,
12
1$
#8
0#
0,
02
0$
0%
#9
b1001110000011 -
1#
1,
12
1$
#10
0#
0,
02
0$
1%
#11
b1001110000010 -
1#
1,
12
1$
#12
0#
0,
02
0$
0%
#13
b1001110000001 -
1#
1,
12
1$
#14
0#
0,
02
0$
1%
#15
b1001110000000 -
1#
1,
12
1$
#16
0#
0,
02
0$
0%
#17
b1001101111111 -
1#
1,
12
1$
#18
0#
0,
02
0$
1%
#19
b1001101111110 -
1#
1,
12
1$
#20
0#
0,
02
0$
0%
#21
b1001101111101 -
1#
1,
12
1$
#22
0#
0,
02
0$
1%
#23
b1001101111100 -
1#
1,
12
1$
#24
0#
0,
02
0$
0%
#25
b1001101111011 -
1#
1,
12
1$
#26
0#
0,
02
0$
1%
#27
b1001101111010 -
1#
1,
12
1$
#28
0#
0,
02
0$
0%
#29
b1001101111001 -
1#
1,
12
1$
#30
0#
0,
02
0$
1%
#31
b1001101111000 -
1#
1,
12
1$
#32
0#
0,
02
0$
0%
#33
b1001101110111 -
1#
1,
12
1$
#34
0#
0,
02
0$
1%
#35
b1001101110110 -
1#
1,
12
1$
#36
0#
0,
02
0$
0%
#37
b1001101110101 -
1#
1,
12
1$
#38
0#
0,
02
0$
1%
#39
b1001101110100 -
1#
1,
12
1$
#40
0#
0,
02
0$
0%
#41
b1001101110011 -
1#
1,
12
1$
#42
0#
0,
02
0$
1%
#43
b1001101110010 -
1#
1,
12
1$
#44
0#
0,
02
0$
0%
#45
b1001101110001 -
1#
1,
12
1$
#46
0#
0,
02
0$
1%
#47
b1001101110000 -
1#
1,
12
1$
#48
0#
0,
02
0$
0%
#49
b1001101101111 -
1#
1,
12
1$
#50
0#
0,
02
0$
1%
#51
b1001101101110 -
1#
1,
12
1$
#52
0#
0,
02
0$
0%
#53
b1001101101101 -
1#
1,
12
1$
#54
0#
0,
02
0$
1%
#55
b1001101101100 -
1#
1,
12
1$
#56
0#
0,
02
0$
0%
#57
b1001101101011 -
1#
1,
12
1$
#58
0#
0,
02
0$
1%
#59
b1001101101010 -
1#
1,
12
1$
#60
0#
0,
02
0$
0%
#61
b1001101101001 -
1#
1,
12
1$
#62
0#
0,
02
0$
1%
#63
b1001101101000 -
1#
1,
12
1$
#64
0#
0,
02
0$
0%
#65
b1001101100111 -
1#
1,
12
1$
#66
0#
0,
02
0$
1%
#67
b1001101100110 -
1#
1,
12
1$
#68
0#
0,
02
0$
0%
#69
b1001101100101 -
1#
1,
12
1$
#70
0#
0,
02
0$
1%
#71
b1001101100100 -
1#
1,
12
1$
#72
0#
0,
02
0$
0%
#73
b1001101100011 -
1#
1,
12
1$
#74
0#
0,
02
0$
1%
#75
b1001101100010 -
1#
1,
12
1$
#76
0#
0,
02
0$
0%
#77
b1001101100001 -
1#
1,
12
1$
#78
0#
0,
02
0$
1%
#79
b1001101100000 -
1#
1,
12
1$
#80
0#
0,
02
0$
0%
#81
b1001101011111 -
1#
1,
12
1$
#82
0#
0,
02
0$
1%
#83
b1001101011110 -
1#
1,
12
1$
#84
0#
0,
02
0$
0%
#85
b1001101011101 -
1#
1,
12
1$
#86
0#
0,
02
0$
1%
#87
b1001101011100 -
1#
1,
12
1$
#88
0#
0,
02
0$
0%
#89
b1001101011011 -
1#
1,
12
1$
#90
0#
0,
02
0$
1%
#91
b1001101011010 -
1#
1,
12
1$
#92
0#
0,
02
0$
0%
#93
b1001101011001 -
1#
1,
12
1$
#94
0#
0,
02
0$
1%
#95
b1001101011000 -
1#
1,
12
1$
#96
0#
0,
02
0$
0%
#97
b1001101010111 -
1#
1,
12
1$
#98
0#
0,
02
0$
1%
#99
b1001101010110 -
1#
1,
12
1$
#100
0#
0,
02
0$
0%
#101
b1001101010101 -
1#
1,
12
1$
#102
0#
0,
02
0$
1%
#103
b1001101010100 -
1#
1,
12
1$
#104
0#
0,
02
0$
0%
#105
b1001101010011 -
1#
1,
12
1$
#106
0#
0,
02
0$
1%
#107
b1001101010010 -
1#
1,
12
1$
#108
0#
0,
02
0$
0%
#109
b1001101010001 -
1#
1,
12
1$
#110
0#
0,
02
0$
1%
#111
b1001101010000 -
1#
1,
12
1$
#112
0#
0,
02
0$
0%
#113
b1001101001111 -
1#
1,
12
1$
#114
0#
0,
02
0$
1%
#115
b1001101001110 -
1#
1,
12
1$
#116
0#
0,
02
0$
0%
#117
b1001101001101 -
1#
1,
12
1$
#118
0#
0,
02
0$
1%
#119
b1001101001100 -
1#
1,
12
1$
#120
0#
0,
02
0$
0%
#121
b1001101001011 -
1#
1,
12
1$
#122
0#
0,
02
0$
1%
#123
b1001101001010 -
1#
1,
12
1$
#124
0#
0,
02
0$
0%
#125
b1001101001001 -
1#
1,
12
1$
#126
0#
0,
02
0$
1%
#127
b1001101001000 -
1#
1,
12
1$
#128
0#
0,
02
0$
0%
#129
b1001101000111 -
1#
1,
12
1$
#130
0#
0,
02
0$
1%
#131
b1001101000110 -
1#
1,
12
1$
#132
0#
0,
02
0$
0%
#133
b1001101000101 -
1#
1,
12
1$
#134
0#
0,
02
0$
1%
#135
b1001101000100 -
1#
1,
12
1$
#136
0#
0,
02
0$
0%
#137
b1001101000011 -
1#
1,
12
1$
#138
0#
0,
02
0$
1%
#139
b1001101000010 -
1#
1,
12
1$
#140
0#
0,
02
0$
0%
#141
b1001101000001 -
1#
1,
12
1$
#142
0#
0,
02
0$
1%
#143
b1001101000000 -
1#
1,
12
1$
#144
0#
0,
02
0$
0%
#145
b1001100111111 -
1#
1,
12
1$
#146
0#
0,
02
0$
1%
#147
b1001100111110 -
1#
1,
12
1$
#148
0#
0,
02
0$
0%
#149
b1001100111101 -
1#
1,
12
1$
#150
0#
0,
02
0$
1%
#151
b1001100111100 -
1#
1,
12
1$
#152
0#
0,
02
0$
0%
#153
b1001100111011 -
1#
1,
12
1$
#154
0#
0,
02
0$
1%
#155
b1001100111010 -
1#
1,
12
1$
#156
0#
0,
02
0$
0%
#157
b1001100111001 -
1#
1,
12
1$
#158
0#
0,
02
0$
1%
#159
b1001100111000 -
1#
1,
12
1$
#160
0#
0,
02
0$
0%
#161
b1001100110111 -
1#
1,
12
1$
#162
0#
0,
02
0$
1%
#163
b1001100110110 -
1#
1,
12
1$
#164
0#
0,
02
0$
0%
#165
b1001100110101 -
1#
1,
12
1$
#166
0#
0,
02
0$
1%
#167
b1001100110100 -
1#
1,
12
1$
#168
0#
0,
02
0$
0%
#169
b1001100110011 -
1#
1,
12
1$
#170
0#
0,
02
0$
1%
#171
b1001100110010 -
1#
1,
12
1$
#172
0#
0,
02
0$
0%
#173
b1001100110001 -
1#
1,
12
1$
#174
0#
0,
02
0$
1%
#175
b1001100110000 -
1#
1,
12
1$
#176
0#
0,
02
0$
0%
#177
b1001100101111 -
1#
1,
12
1$
#178
0#
0,
02
0$
1%
#179
b1001100101110 -
1#
1,
12
1$
#180
0#
0,
02
0$
0%
#181
b1001100101101 -
1#
1,
12
1$
#182
0#
0,
02
0$
1%
#183
b1001100101100 -
1#
1,
12
1$
#184
0#
0,
02
0$
0%
#185
b1001100101011 -
1#
1,
12
1$
#186
0#
0,
02
0$
1%
#187
b1001100101010 -
1#
1,
12
1$
#188
0#
0,
02
0$
0%
#189
b1001100101001 -
1#
1,
12
1$
#190
0#
0,
02
0$
1%
#191
b1001100101000 -
1#
1,
12
1$
#192
0#
0,
02
0$
0%
#193
b1001100100111 -
1#
1,
12
1$
#194
0#
0,
02
0$
1%
#195
b1001100100110 -
1#
1,
12
1$
#196
0#
0,
02
0$
0%
#197
b1001100100101 -
1#
1,
12
1$
#198
0#
0,
02
0$
1%
#199
b1001100100100 -
1#
1,
12
1$
#200
0#
0,
02
0$
0%
#201
b1001100100011 -
1#
1,
12
1$
#202
0#
0,
02
0$
1%
#203
b1001100100010 -
1#
1,
12
1$
#204
0#
0,
02
0$
0%
#205
b1001100100001 -
1#
1,
12
1$
#206
0#
0,
02
0$
1%
#207
b1001100100000 -
1#
1,
12
1$
#208
0#
0,
02
0$
0%
#209
b1001100011111 -
1#
1,
12
1$
#210
0#
0,
02
0$
1%
#211
b1001100011110 -
1#
1,
12
1$
#212
0#
0,
02
0$
0%
#213
b1001100011101 -
1#
1,
12
1$
#214
0#
0,
02
0$
1%
#215
b1001100011100 -
1#
1,
12
1$
#216
0#
0,
02
0$
0%
#217
b1001100011011 -
1#
1,
12
1$
#218
0#
0,
02
0$
1%
#219
b1001100011010 -
1#
1,
12
1$
#220
0#
0,
02
0$
0%
#221
b1001100011001 -
1#
1,
12
1$
#222
0#
0,
02
0$
1%
#223
b1001100011000 -
1#
1,
12
1$
#224
0#
0,
02
0$
0%
#225
b1001100010111 -
1#
1,
12
1$
#226
0#
0,
02
0$
1%
#227
b1001100010110 -
1#
1,
12
1$
#228
0#
0,
02
0$
0%
#229
b1001100010101 -
1#
1,
12
1$
#230
0#
0,
02
0$
1%
#231
b1001100010100 -
1#
1,
12
1$
#232
0#
0,
02
0$
0%
#233
b1001100010011 -
1#
1,
12
1$
#234
0#
0,
02
0$
1%
#235
b1001100010010 -
1#
1,
12
1$
#236
0#
0,
02
0$
0%
#237
b1001100010001 -
1#
1,
12
1$
#238
0#
0,
02
0$
1%
#239
b1001100010000 -
1#
1,
12
1$
#240
0#
0,
02
0$
0%
#241
b1001100001111 -
1#
1,
12
1$
#242
0#
0,
02
0$
1%
#243
b1001100001110 -
1#
1,
12
1$
#244
0#
0,
02
0$
0%
#245
b1001100001101 -
1#
1,
12
1$
#246
0#
0,
02
0$
1%
#247
b1001100001100 -
1#
1,
12
1$
#248
0#
0,
02
0$
0%
#249
b1001100001011 -
1#
1,
12
1$
#250
0#
0,
02
0$
1%
#251
b1001100001010 -
1#
1,
12
1$
#252
0#
0,
02
0$
0%
#253
b1001100001001 -
1#
1,
12
1$
#254
0#
0,
02
0$
1%
#255
b1001100001000 -
1#
1,
12
1$
#256
0#
0,
02
0$
0%
#257
b1001100000111 -
1#
1,
12
1$
#258
0#
0,
02
0$
1%
#259
b1001100000110 -
1#
1,
12
1$
#260
0#
0,
02
0$
0%
#261
b1001100000101 -
1#
1,
12
1$
#262
0#
0,
02
0$
1%
#263
b1001100000100 -
1#
1,
12
1$
#264
0#
0,
02
0$
0%
#265
b1001100000011 -
1#
1,
12
1$
#266
0#
0,
02
0$
1%
#267
b1001100000010 -
1#
1,
12
1$
#268
0#
0,
02
0$
0%
#269
b1001100000001 -
1#
1,
12
1$
#270
0#
0,
02
0$
1%
#271
b1001100000000 -
1#
1,
12
1$
#272
0#
0,
02
0$
0%
#273
b1001011111111 -
1#
1,
12
1$
#274
0#
0,
02
0$
1%
#275
b1001011111110 -
1#
1,
12
1$
#276
0#
0,
02
0$
0%
#277
b1001011111101 -
1#
1,
12
1$
#278
0#
0,
02
0$
1%
#279
b1001011111100 -
1#
1,
12
1$
#280
0#
0,
02
0$
0%
#281
b1001011111011 -
1#
1,
12
1$
#282
0#
0,
02
0$
1%
#283
b1001011111010 -
1#
1,
12
1$
#284
0#
0,
02
0$
0%
#285
b1001011111001 -
1#
1,
12
1$
#286
0#
0,
02
0$
1%
#287
b1001011111000 -
1#
1,
12
1$
#288
0#
0,
02
0$
0%
#289
b1001011110111 -
1#
1,
12
1$
#290
0#
0,
02
0$
1%
#291
b1001011110110 -
1#
1,
12
1$
#292
0#
0,
02
0$
0%
#293
b1001011110101 -
1#
1,
12
1$
#294
0#
0,
02
0$
1%
#295
b1001011110100 -
1#
1,
12
1$
#296
0#
0,
02
0$
0%
#297
b1001011110011 -
1#
1,
12
1$
#298
0#
0,
02
0$
1%
#299
b1001011110010 -
1#
1,
12
1$
#300
0#
0,
02
0$
0%
#301
b1001011110001 -
1#
1,
12
1$
#302
0#
0,
02
0$
1%
#303
b1001011110000 -
1#
1,
12
1$
#304
0#
0,
02
0$
0%
#305
b1001011101111 -
1#
1,
12
1$
#306
0#
0,
02
0$
1%
#307
b1001011101110 -
1#
1,
12
1$
#308
0#
0,
02
0$
0%
#309
b1001011101101 -
1#
1,
12
1$
#310
0#
0,
02
0$
1%
#311
b1001011101100 -
1#
1,
12
1$
#312
0#
0,
02
0$
0%
#313
b1001011101011 -
1#
1,
12
1$
#314
0#
0,
02
0$
1%
#315
b1001011101010 -
1#
1,
12
1$
#316
0#
0,
02
0$
0%
#317
b1001011101001 -
1#
1,
12
1$
#318
0#
0,
02
0$
1%
#319
b1001011101000 -
1#
1,
12
1$
#320
0#
0,
02
0$
0%
#321
b1001011100111 -
1#
1,
12
1$
#322
0#
0,
02
0$
1%
#323
b1001011100110 -
1#
1,
12
1$
#324
0#
0,
02
0$
0%
#325
b1001011100101 -
1#
1,
12
1$
#326
0#
0,
02
0$
1%
#327
b1001011100100 -
1#
1,
12
1$
#328
0#
0,
02
0$
0%
#329
b1001011100011 -
1#
1,
12
1$
#330
0#
0,
02
0$
1%
#331
b1001011100010 -
1#
1,
12
1$
#332
0#
0,
02
0$
0%
#333
b1001011100001 -
1#
1,
12
1$
#334
0#
0,
02
0$
1%
#335
b1001011100000 -
1#
1,
12
1$
#336
0#
0,
02
0$
0%
#337
b1001011011111 -
1#
1,
12
1$
#338
0#
0,
02
0$
1%
#339
b1001011011110 -
1#
1,
12
1$
#340
0#
0,
02
0$
0%
#341
b1001011011101 -
1#
1,
12
1$
#342
0#
0,
02
0$
1%
#343
b1001011011100 -
1#
1,
12
1$
#344
0#
0,
02
0$
0%
#345
b1001011011011 -
1#
1,
12
1$
#346
0#
0,
02
0$
1%
#347
b1001011011010 -
1#
1,
12
1$
#348
0#
0,
02
0$
0%
#349
b1001011011001 -
1#
1,
12
1$
#350
0#
0,
02
0$
1%
#351
b1001011011000 -
1#
1,
12
1$
#352
0#
0,
02
0$
0%
#353
b1001011010111 -
1#
1,
12
1$
#354
0#
0,
02
0$
1%
#355
b1001011010110 -
1#
1,
12
1$
#356
0#
0,
02
0$
0%
#357
b1001011010101 -
1#
1,
12
1$
#358
0#
0,
02
0$
1%
#359
b1001011010100 -
1#
1,
12
1$
#360
0#
0,
02
0$
0%
#361
b1001011010011 -
1#
1,
12
1$
#362
0#
0,
02
0$
1%
#363
b1001011010010 -
1#
1,
12
1$
#364
0#
0,
02
0$
0%
#365
b1001011010001 -
1#
1,
12
1$
#366
0#
0,
02
0$
1%
#367
b1001011010000 -
1#
1,
12
1$
#368
0#
0,
02
0$
0%
#369
b1001011001111 -
1#
1,
12
1$
#370
0#
0,
02
0$
1%
#371
b1001011001110 -
1#
1,
12
1$
#372
0#
0,
02
0$
0%
#373
b1001011001101 -
1#
1,
12
1$
#374
0#
0,
02
0$
1%
#375
b1001011001100 -
1#
1,
12
1$
#376
0#
0,
02
0$
0%
#377
b1001011001011 -
1#
1,
12
1$
#378
0#
0,
02
0$
1%
#379
b1001011001010 -
1#
1,
12
1$
#380
0#
0,
02
0$
0%
#381
b1001011001001 -
1#
1,
12
1$
#382
0#
0,
02
0$
1%
#383
b1001011001000 -
1#
1,
12
1$
#384
0#
0,
02
0$
0%
#385
b1001011000111 -
1#
1,
12
1$
#386
0#
0,
02
0$
1%
#387
b1001011000110 -
1#
1,
12
1$
#388
0#
0,
02
0$
0%
#389
b1001011000101 -
1#
1,
12
1$
#390
0#
0,
02
0$
1%
#391
b1001011000100 -
1#
1,
12
1$
#392
0#
0,
02
0$
0%
#393
b1001011000011 -
1#
1,
12
1$
#394
0#
0,
02
0$
1%
#395
b1001011000010 -
1#
1,
12
1$
#396
0#
0,
02
0$
0%
#397
b1001011000001 -
1#
1,
12
1$
#398
0#
0,
02
0$
1%
#399
b1001011000000 -
1#
1,
12
1$
#400
0#
0,
02
0$
0%
#401
b1001010111111 -
1#
1,
12
1$
#402
0#
0,
02
0$
1%
#403
b1001010111110 -
1#
1,
12
1$
#404
0#
0,
02
0$
0%
#405
b1001010111101 -
1#
1,
12
1$
#406
0#
0,
02
0$
1%
#407
b1001010111100 -
1#
1,
12
1$
#408
0#
0,
02
0$
0%
#409
b1001010111011 -
1#
1,
12
1$
#410
0#
0,
02
0$
1%
#411
b1001010111010 -
1#
1,
12
1$
#412
0#
0,
02
0$
0%
#413
b1001010111001 -
1#
1,
12
1$
#414
0#
0,
02
0$
1%
#415
b1001010111000 -
1#
1,
12
1$
#416
0#
0,
02
0$
0%
#417
b1001010110111 -
1#
1,
12
1$
#418
0#
0,
02
0$
1%
#419
b1001010110110 -
1#
1,
12
1$
#420
0#
0,
02
0$
0%
#421
b1001010110101 -
1#
1,
12
1$
#422
0#
0,
02
0$
1%
#423
b1001010110100 -
1#
1,
12
1$
#424
0#
0,
02
0$
0%
#425
b1001010110011 -
1#
1,
12
1$
#426
0#
0,
02
0$
1%
#427
b1001010110010 -
1#
1,
12
1$
#428
0#
0,
02
0$
0%
#429
b1001010110001 -
1#
1,
12
1$
#430
0#
0,
02
0$
1%
#431
b1001010110000 -
1#
1,
12
1$
#432
0#
0,
02
0$
0%
#433
b1001010101111 -
1#
1,
12
1$
#434
0#
0,
02
0$
1%
#435
b1001010101110 -
1#
1,
12
1$
#436
0#
0,
02
0$
0%
#437
b1001010101101 -
1#
1,
12
1$
#438
0#
0,
02
0$
1%
#439
b1001010101100 -
1#
1,
12
1$
#440
0#
0,
02
0$
0%
#441
b1001010101011 -
1#
1,
12
1$
#442
0#
0,
02
0$
1%
#443
b1001010101010 -
1#
1,
12
1$
#444
0#
0,
02
0$
0%
#445
b1001010101001 -
1#
1,
12
1$
#446
0#
0,
02
0$
1%
#447
b1001010101000 -
1#
1,
12
1$
#448
0#
0,
02
0$
0%
#449
b1001010100111 -
1#
1,
12
1$
#450
0#
0,
02
0$
1%
#451
b1001010100110 -
1#
1,
12
1$
#452
0#
0,
02
0$
0%
#453
b1001010100101 -
1#
1,
12
1$
#454
0#
0,
02
0$
1%
#455
b1001010100100 -
1#
1,
12
1$
#456
0#
0,
02
0$
0%
#457
b1001010100011 -
1#
1,
12
1$
#458
0#
0,
02
0$
1%
#459
b1001010100010 -
1#
1,
12
1$
#460
0#
0,
02
0$
0%
#461
b1001010100001 -
1#
1,
12
1$
#462
0#
0,
02
0$
1%
#463
b1001010100000 -
1#
1,
12
1$
#464
0#
0,
02
0$
0%
#465
b1001010011111 -
1#
1,
12
1$
#466
0#
0,
02
0$
1%
#467
b1001010011110 -
1#
1,
12
1$
#468
0#
0,
02
0$
0%
#469
b1001010011101 -
1#
1,
12
1$
#470
0#
0,
02
0$
1%
#471
b1001010011100 -
1#
1,
12
1$
#472
0#
0,
02
0$
0%
#473
b1001010011011 -
1#
1,
12
1$
#474
0#
0,
02
0$
1%
#475
b1001010011010 -
1#
1,
12
1$
#476
0#
0,
02
0$
0%
#477
b1001010011001 -
1#
1,
12
1$
#478
0#
0,
02
0$
1%
#479
b1001010011000 -
1#
1,
12
1$
#480
0#
0,
02
0$
0%
#481
b1001010010111 -
1#
1,
12
1$
#482
0#
0,
02
0$
1%
#483
b1001010010110 -
1#
1,
12
1$
#484
0#
0,
02
0$
0%
#485
b1001010010101 -
1#
1,
12
1$
#486
0#
0,
02
0$
1%
#487
b1001010010100 -
1#
1,
12
1$
#488
0#
0,
02
0$
0%
#489
b1001010010011 -
1#
1,
12
1$
#490
0#
0,
02
0$
1%
#491
b1001010010010 -
1#
1,
12
1$
#492
0#
0,
02
0$
0%
#493
b1001010010001 -
1#
1,
12
1$
#494
0#
0,
02
0$
1%
#495
b1001010010000 -
1#
1,
12
1$
#496
0#
0,
02
0$
0%
#497
b1001010001111 -
1#
1,
12
1$
#498
0#
0,
02
0$
1%
#499
b1001010001110 -
1#
1,
12
1$
#500
0#
0,
02
0$
0%
#501
b1001010001101 -
1#
1,
12
1$
#502
0#
0,
02
0$
1%
#503
b1001010001100 -
1#
1,
12
1$
#504
0#
0,
02
0$
0%
#505
b1001010001011 -
1#
1,
12
1$
#506
0#
0,
02
0$
1%
#507
b1001010001010 -
1#
1,
12
1$
#508
0#
0,
02
0$
0%
#509
b1001010001001 -
1#
1,
12
1$
#510
0#
0,
02
0$
1%
#511
b1001010001000 -
1#
1,
12
1$
#512
0#
0,
02
0$
0%
#513
b1001010000111 -
1#
1,
12
1$
#514
0#
0,
02
0$
1%
#515
b1001010000110 -
1#
1,
12
1$
#516
0#
0,
02
0$
0%
#517
b1001010000101 -
1#
1,
12
1$
#518
0#
0,
02
0$
1%
#519
b1001010000100 -
1#
1,
12
1$
#520
0#
0,
02
0$
0%
#521
b1001010000011 -
1#
1,
12
1$
#522
0#
0,
02
0$
1%
#523
b1001010000010 -
1#
1,
12
1$
#524
0#
0,
02
0$
0%
#525
b1001010000001 -
1#
1,
12
1$
#526
0#
0,
02
0$
1%
#527
b1001010000000 -
1#
1,
12
1$
#528
0#
0,
02
0$
0%
#529
b1001001111111 -
1#
1,
12
1$
#530
0#
0,
02
0$
1%
#531
b1001001111110 -
1#
1,
12
1$
#532
0#
0,
02
0$
0%
#533
b1001001111101 -
1#
1,
12
1$
#534
0#
0,
02
0$
1%
#535
b1001001111100 -
1#
1,
12
1$
#536
0#
0,
02
0$
0%
#537
b1001001111011 -
1#
1,
12
1$
#538
0#
0,
02
0$
1%
#539
b1001001111010 -
1#
1,
12
1$
#540
0#
0,
02
0$
0%
#541
b1001001111001 -
1#
1,
12
1$
#542
0#
0,
02
0$
1%
#543
b1001001111000 -
1#
1,
12
1$
#544
0#
0,
02
0$
0%
#545
b1001001110111 -
1#
1,
12
1$
#546
0#
0,
02
0$
1%
#547
b1001001110110 -
1#
1,
12
1$
#548
0#
0,
02
0$
0%
#549
b1001001110101 -
1#
1,
12
1$
#550
0#
0,
02
0$
1%
#551
b1001001110100 -
1#
1,
12
1$
#552
0#
0,
02
0$
0%
#553
b1001001110011 -
1#
1,
12
1$
#554
0#
0,
02
0$
1%
#555
b1001001110010 -
1#
1,
12
1$
#556
0#
0,
02
0$
0%
#557
b1001001110001 -
1#
1,
12
1$
#558
0#
0,
02
0$
1%
#559
b1001001110000 -
1#
1,
12
1$
#560
0#
0,
02
0$
0%
#561
b1001001101111 -
1#
1,
12
1$
#562
0#
0,
02
0$
1%
#563
b1001001101110 -
1#
1,
12
1$
#564
0#
0,
02
0$
0%
#565
b1001001101101 -
1#
1,
12
1$
#566
0#
0,
02
0$
1%
#567
b1001001101100 -
1#
1,
12
1$
#568
0#
0,
02
0$
0%
#569
b1001001101011 -
1#
1,
12
1$
#570
0#
0,
02
0$
1%
#571
b1001001101010 -
1#
1,
12
1$
#572
0#
0,
02
0$
0%
#573
b1001001101001 -
1#
1,
12
1$
#574
0#
0,
02
0$
1%
#575
b1001001101000 -
1#
1,
12
1$
#576
0#
0,
02
0$
0%
#577
b1001001100111 -
1#
1,
12
1$
#578
0#
0,
02
0$
1%
#579
b1001001100110 -
1#
1,
12
1$
#580
0#
0,
02
0$
0%
#581
b1001001100101 -
1#
1,
12
1$
#582
0#
0,
02
0$
1%
#583
b1001001100100 -
1#
1,
12
1$
#584
0#
0,
02
0$
0%
#585
b1001001100011 -
1#
1,
12
1$
#586
0#
0,
02
0$
1%
#587
b1001001100010 -
1#
1,
12
1$
#588
0#
0,
02
0$
0%
#589
b1001001100001 -
1#
1,
12
1$
#590
0#
0,
02
0$
1%
#591
b1001001100000 -
1#
1,
12
1$
#592
0#
0,
02
0$
0%
#593
b1001001011111 -
1#
1,
12
1$
#594
0#
0,
02
0$
1%
#595
b1001001011110 -
1#
1,
12
1$
#596
0#
0,
02
0$
0%
#597
b1001001011101 -
1#
1,
12
1$
#598
0#
0,
02
0$
1%
#599
b1001001011100 -
1#
1,
12
1$
#600
0#
0,
02
0$
0%
#601
b1001001011011 -
1#
1,
12
1$
#602
0#
0,
02
0$
1%
#603
b1001001011010 -
1#
1,
12
1$
#604
0#
0,
02
0$
0%
#605
b1001001011001 -
1#
1,
12
1$
#606
0#
0,
02
0$
1%
#607
b1001001011000 -
1#
1,
12
1$
#608
0#
0,
02
0$
0%
#609
b1001001010111 -
1#
1,
12
1$
#610
0#
0,
02
0$
1%
